mulan/__init__.py
mulan/orm/__init__.py
mulan/orm/models.py
mulanci-0.1.1.dist-info/WHEEL
mulanci-0.1.1.dist-info/METADATA
mulanci-0.1.1.dist-info/RECORD
