Metadata-Version: 2.3
Name: mulanci
Version: 0.1.1
Summary: Add your description here
Requires-Dist: peewee>=3.18.2
Requires-Python: >=3.13
